grpc_client/__init__.py
allure_grpc_client-25.298.dist-info/METADATA
allure_grpc_client-25.298.dist-info/WHEEL
allure_grpc_client-25.298.dist-info/licenses/LICENSE
allure_grpc_client-25.298.dist-info/RECORD
