Metadata-Version: 2.4
Name: allure-grpc-client
Version: 25.298
Summary: 
License-File: LICENSE
Author: amaym0n
Author-email: loco.skitls@gmail.com
Classifier: Programming Language :: Python :: 2
Classifier: Programming Language :: Python :: 2.7
Classifier: Programming Language :: Python :: 3
Classifier: Programming Language :: Python :: 3.4
Classifier: Programming Language :: Python :: 3.5
Classifier: Programming Language :: Python :: 3.6
Classifier: Programming Language :: Python :: 3.7
Classifier: Programming Language :: Python :: 3.8
Classifier: Programming Language :: Python :: 3.9
Classifier: Programming Language :: Python :: 3.10
Classifier: Programming Language :: Python :: 3.11
Classifier: Programming Language :: Python :: 3.12
Classifier: Programming Language :: Python :: 3.13
Classifier: Programming Language :: Python :: 3.14
Requires-Dist: allure-pytest ; python_version >= "3.11" and python_version < "4.0"
Requires-Dist: certifi ; python_version >= "3.11" and python_version < "4.0"
Requires-Dist: grpcio ; python_version >= "3.11" and python_version < "4.0"
Requires-Dist: grpcio-reflection ; python_version >= "3.11" and python_version < "4.0"
